liminal/__init__.py
liminal/auth/__init__.py
liminal/auth/microsoft/__init__.py
liminal/auth/microsoft/device_code_flow.py
liminal/auth/microsoft/models.py
liminal/client.py
liminal/const.py
liminal/endpoints/__init__.py
liminal/endpoints/llm/__init__.py
liminal/endpoints/llm/models.py
liminal/endpoints/llm/schemas.py
liminal/endpoints/prompt/__init__.py
liminal/endpoints/prompt/models.py
liminal/endpoints/prompt/schemas.py
liminal/endpoints/thread/__init__.py
liminal/endpoints/thread/models.py
liminal/endpoints/thread/schemas.py
liminal/errors.py
liminal/helpers/__init__.py
liminal/helpers/model.py
liminal/helpers/schema.py
liminal/helpers/typing.py
liminal_sdk_python-2025.5.0.dist-info/LICENSE
liminal_sdk_python-2025.5.0.dist-info/METADATA
liminal_sdk_python-2025.5.0.dist-info/WHEEL
liminal_sdk_python-2025.5.0.dist-info/RECORD
