Metadata-Version: 2.3
Name: liminal-sdk-python
Version: 2025.5.0
Summary: The Liminal SDK for Python
License: Apache-2.0
Author: Liminal AI
Author-email: info@liminal.ai
Requires-Python: >=3.11,<3.14
Classifier: License :: OSI Approved :: Apache Software License
Classifier: Programming Language :: Python
Classifier: Programming Language :: Python :: 3
Classifier: Programming Language :: Python :: 3.11
Classifier: Programming Language :: Python :: 3.12
Classifier: Programming Language :: Python :: 3.13
Classifier: Programming Language :: Python :: Implementation :: CPython
Classifier: Programming Language :: Python :: Implementation :: PyPy
Provides-Extra: all
Provides-Extra: build
Provides-Extra: lint
Provides-Extra: release
Provides-Extra: test
Requires-Dist: anyio (>=4.4.0)
Requires-Dist: blacken-docs (==1.19.1) ; extra == "lint"
Requires-Dist: codespell (==2.4.1) ; extra == "lint"
Requires-Dist: cryptography (==43.0.3)
Requires-Dist: darglint (==1.8.1) ; extra == "lint"
Requires-Dist: httpx (==0.28.1)
Requires-Dist: liminal-sdk-python[build,lint,release,test] ; extra == "all"
Requires-Dist: mashumaro (==3.15)
Requires-Dist: msal (==1.32.3)
Requires-Dist: mypy (==1.15.0) ; extra == "lint"
Requires-Dist: pre-commit (==4.2.0) ; extra == "lint"
Requires-Dist: pre-commit-hooks (==5.0.0) ; extra == "lint"
Requires-Dist: pylint (==3.3.7) ; extra == "lint"
Requires-Dist: pytest (==8.3.5) ; extra == "lint"
Requires-Dist: pytest (==8.3.5) ; extra == "test"
Requires-Dist: pytest-asyncio (==0.26.0) ; extra == "lint"
Requires-Dist: pytest-asyncio (==0.26.0) ; extra == "test"
Requires-Dist: pytest-cov (==6.1.1) ; extra == "test"
Requires-Dist: pytest-httpx (==0.35.0) ; extra == "test"
Requires-Dist: requests (>=2.32.2)
Requires-Dist: ruff (==0.11.8) ; extra == "lint"
Requires-Dist: tomli (==2.2.1) ; extra == "release"
Requires-Dist: tomli-w (==1.2.0) ; extra == "release"
Requires-Dist: uv (==0.7.2) ; extra == "build"
